{"type": "Feature", "id": 12512486, "geometry": {"type": "Point", "coordinates": [-79.779999, 21.7397]}, "properties": {"woe:id": 12512486, "woe:parent_id": 67564, "woe:name": "San Pedro Airport", "woe:placetype": 14, "woe:placetype_name": "Airport", "woe:lang": "ENG", "iso:country": "CU", "meta:provider": ["geoplanet:7.3.1", "geoplanet:7.3.2", "geoplanet:7.4.0", "geoplanet:7.4.1", "geoplanet:7.5.1", "geoplanet:7.5.2", "geoplanet:7.6.0", "geoplanet:7.8.1", "geoplanet:7.9.0", "geoplanet:7.10.0", "geoplanet:8.0.0", "woeplanet:8.0.0"], "meta:indexed": "2020-08-20T20:25:58.197073", "meta:updated": "2020-10-14T12:07:00.054965", "woe:hierarchy": {"continent": 24865672, "country": 23424793, "town": 0, "planet": 1, "county": 0, "suburb": 0, "state": 2345118, "region": 0, "localadmin": 0}, "woe:timezone_id": 28350765, "woe:hash": "d5z78t9fzmc1", "woe:centroid": [-79.779999, 21.7397], "geom:latitude": 21.7397, "geom:longitude": -79.779999, "geom:hash": "d5z78t9fzmc1", "woe:latitude": 21.7397, "geom:centroid": [-79.779999, 21.7397], "woe:longitude": -79.779999, "woe:repo": "woeplanet-airport-cu", "geom:area": 0.0, "woe:scale": 19}}