{"type": "Feature", "id": 12512451, "geometry": {"type": "Point", "coordinates": [-82.734703, 22.752199]}, "properties": {"woe:id": 12512451, "woe:parent_id": 66540, "woe:name": "Artemisa Airport", "woe:placetype": 14, "woe:placetype_name": "Airport", "woe:lang": "ENG", "iso:country": "CU", "meta:provider": ["geoplanet:7.3.1", "geoplanet:7.3.2", "geoplanet:7.4.0", "geoplanet:7.4.1", "geoplanet:7.5.1", "geoplanet:7.5.2", "geoplanet:7.6.0", "geoplanet:7.8.1", "geoplanet:7.9.0", "geoplanet:7.10.0", "geoplanet:8.0.0", "woeplanet:8.0.0"], "meta:indexed": "2020-08-20T20:25:58.167998", "meta:updated": "2020-10-14T12:07:00.065693", "woe:hierarchy": {"continent": 24865672, "country": 23424793, "town": 0, "planet": 1, "county": 0, "suburb": 0, "state": 2345115, "region": 0, "localadmin": 0}, "woe:timezone_id": 28350765, "woe:hash": "dhj1mmfmjtq1", "woe:centroid": [-82.734703, 22.752199], "geom:latitude": 22.752199, "geom:longitude": -82.734703, "geom:hash": "dhj1mmfmjtq1", "woe:latitude": 22.752199, "geom:centroid": [-82.734703, 22.752199], "woe:longitude": -82.734703, "woe:repo": "woeplanet-airport-cu", "geom:area": 0.0, "woe:scale": 19}}